zhouatie_cao/__init__.py
zhouatie_cao/__main__.py
zhouatie_cao/ai_client.py
zhouatie_cao/cli.py
zhouatie_cao/config.py
zhouatie_cao/config_cli.py
zhouatie_cao/main.py
zhouatie_cao/cli/__init__.py
zhouatie_cao/cli/interactive.py
zhouatie_cao/cli/main.py
zhouatie_cao/cli/parser.py
zhouatie_cao/utils/__init__.py
zhouatie_cao/utils/command.py
zhouatie_cao/utils/logger.py
zhouatie_cao/utils/terminal.py
zhouatie_cao-1.0.15.dist-info/licenses/LICENSE
zhouatie_cao-1.0.15.dist-info/METADATA
zhouatie_cao-1.0.15.dist-info/WHEEL
zhouatie_cao-1.0.15.dist-info/entry_points.txt
zhouatie_cao-1.0.15.dist-info/top_level.txt
zhouatie_cao-1.0.15.dist-info/RECORD
